find_duplicate_files.py
find_duplicate_files-2.1.0.data/scripts/find_duplicate_files
find_duplicate_files-2.1.0.dist-info/LICENSE
find_duplicate_files-2.1.0.dist-info/METADATA
find_duplicate_files-2.1.0.dist-info/WHEEL
find_duplicate_files-2.1.0.dist-info/top_level.txt
find_duplicate_files-2.1.0.dist-info/RECORD
