Metadata-Version: 2.1
Name: find-duplicate-files
Version: 2.1.0
Summary: Module to find duplicate files in a directory
Home-page: https://github.com/hp310780/FindDuplicateFiles
Author: hp310780
License: MIT License
Platform: UNKNOWN
Classifier: Programming Language :: Python :: 3
